char_art/__init__.py
char_art/__init__.pyi
char_art/__main__.py
char_art/__main__.pyi
char_art/_pygame.py
char_art-0.1.1.dist-info/LICENSE
char_art-0.1.1.dist-info/METADATA
char_art-0.1.1.dist-info/WHEEL
char_art-0.1.1.dist-info/top_level.txt
char_art-0.1.1.dist-info/RECORD
