Metadata-Version: 2.2
Name: char_art
Version: 0.1.1
Summary: 方便地制作字符画与字符视频 ~
Author-email: Liu Wei <23S112099@stu.hit.edu.cn>
Maintainer-email: Liu Wei <23S112099@stu.hit.edu.cn>
License: MIT License
Project-URL: Homepage, https://github.com/AomandeNiuma/char_art
Keywords: char_art,character image,character video
Classifier: License :: OSI Approved :: MIT License
Classifier: Programming Language :: Python :: 3
Classifier: Programming Language :: Python :: 3.6
Classifier: Programming Language :: Python :: 3.7
Classifier: Programming Language :: Python :: 3.8
Classifier: Programming Language :: Python :: 3.9
Classifier: Programming Language :: Python :: 3.10
Classifier: Programming Language :: Python :: 3.11
Classifier: Programming Language :: Python :: 3.12
Classifier: Programming Language :: Python :: 3.13
Requires-Python: >=3.7.0
License-File: LICENSE
Requires-Dist: opencv-python
Requires-Dist: numpy
Provides-Extra: save
Requires-Dist: pygame; extra == "save"
